traindiagnostics/__init__.py
traindiagnostics/__version__.py
traindiagnostics/businessrules.py
traindiagnostics/errors.py
traindiagnostics/event.py
traindiagnostics/fleet.py
traindiagnostics/report.py
traindiagnostics/timeseries.py
traindiagnostics/types.py
traindiagnostics-0.3.0.dist-info/LICENSE
traindiagnostics-0.3.0.dist-info/METADATA
traindiagnostics-0.3.0.dist-info/WHEEL
traindiagnostics-0.3.0.dist-info/top_level.txt
traindiagnostics-0.3.0.dist-info/RECORD
