Metadata-Version: 2.1
Name: traindiagnostics
Version: 0.3.0
Summary: A toolbox to analyse diagnostic train data!
Home-page: https://github.com/timolesterhuis/traindiagnostics/
Author: Timo Lesterhuis
Author-email: Timo.Lesterhuis@gmail.com
License: GNU GPLv3
Project-URL: Source, https://github.com/timolesterhuis/traindiagnostics
Project-URL: Issue Tracker, https://github.com/timolesterhuis/traindiagnostics/issues
Platform: UNKNOWN
Classifier: Programming Language :: Python :: 3 :: Only
Classifier: Programming Language :: Python :: 3.5
Classifier: Programming Language :: Python :: 3.6
Classifier: Programming Language :: Python :: 3.7
Classifier: Programming Language :: Python :: 3.8
Classifier: License :: OSI Approved :: GNU General Public License v3 (GPLv3)
Classifier: Operating System :: OS Independent
Requires-Dist: ticts (>=0.3.3)
